setup.py
lk_distributions/Binomialdistribution.py
lk_distributions/Gaussiandistribution.py
lk_distributions/Generaldistribution.py
lk_distributions/__init__.py
lk_distributions.egg-info/PKG-INFO
lk_distributions.egg-info/SOURCES.txt
lk_distributions.egg-info/dependency_links.txt
lk_distributions.egg-info/not-zip-safe
lk_distributions.egg-info/top_level.txt