Metadata-Version: 1.0
Name: lk-distributions
Version: 5.1
Summary: Gaussian distributions
Home-page: UNKNOWN
Author: Lokesh Kumar
Author-email: hifilokesh@gmail.com
License: UNKNOWN
Platform: UNKNOWN
